<!--

OGen
Copyright (c) 2002 Francisco Monteiro

Permission is hereby granted, free of charge, to any person obtaining a copy of this software and associated documentation files (the "Software"), to deal in the Software without restriction, including without limitation the rights to use, copy, modify, merge, publish, distribute, sublicense, and/or sell copies of the Software, and to permit persons to whom the Software is furnished to do so, subject to the following conditions:

The above copyright notice and this permission notice shall be included in all copies or substantial portions of the Software.

THE SOFTWARE IS PROVIDED "AS IS", WITHOUT WARRANTY OF ANY KIND, EXPRESS OR IMPLIED, INCLUDING BUT NOT LIMITED TO THE WARRANTIES OF MERCHANTABILITY, FITNESS FOR A PARTICULAR PURPOSE AND NONINFRINGEMENT. IN NO EVENT SHALL THE AUTHORS OR COPYRIGHT HOLDERS BE LIABLE FOR ANY CLAIM, DAMAGES OR OTHER LIABILITY, WHETHER IN AN ACTION OF CONTRACT, TORT OR OTHERWISE, ARISING FROM, OUT OF OR IN CONNECTION WITH THE SOFTWARE OR THE USE OR OTHER DEALINGS IN THE SOFTWARE.

-->
<metadata
	applicationName="NTier_metadata" 
	namespace="OGen.NTier.lib.metadata" 
	caseType="PascalCase"
	allowSettersOnObjects="false"
	isSimple="false"
	prefix="XS_"
	prefixGenerated="XS0_"
	prefixBase="XS__"
	prefixBaseGenerated="XS0__"
	copyrightText="Copyright (C) 2002 Francisco Monteiro">
	<copyrightTextLong>OGen
Copyright (c) 2002 Francisco Monteiro

Permission is hereby granted, free of charge, to any person obtaining a copy of this software and associated documentation files (the &quot;Software&quot;), to deal in the Software without restriction, including without limitation the rights to use, copy, modify, merge, publish, distribute, sublicense, and/or sell copies of the Software, and to permit persons to whom the Software is furnished to do so, subject to the following conditions:

The above copyright notice and this permission notice shall be included in all copies or substantial portions of the Software.

THE SOFTWARE IS PROVIDED &quot;AS IS&quot;, WITHOUT WARRANTY OF ANY KIND, EXPRESS OR IMPLIED, INCLUDING BUT NOT LIMITED TO THE WARRANTIES OF MERCHANTABILITY, FITNESS FOR A PARTICULAR PURPOSE AND NONINFRINGEMENT. IN NO EVENT SHALL THE AUTHORS OR COPYRIGHT HOLDERS BE LIABLE FOR ANY CLAIM, DAMAGES OR OTHER LIABILITY, WHETHER IN AN ACTION OF CONTRACT, TORT OR OTHERWISE, ARISING FROM, OUT OF OR IN CONNECTION WITH THE SOFTWARE OR THE USE OR OTHER DEALINGS IN THE SOFTWARE.</copyrightTextLong>


<!--
ToDos: here!

rename:
	<metadataIndex metadata="metadata" index="ApplicationName" />
	<metadata name="metadata" indexPath="ApplicationName" />
-->
<!--
	<metadataIndex metadata="metadata" index="ApplicationName">
		<specificCase word="db" translation="DB" />
		<specificCase word="dbCollationName" translation="DBCollationName" />

		<complexType name="dbConnectionType">
			<complexTypeKey name="configMode" caseSensitive="false" />
		</complexType>

		<complexType name="dbType">
			<complexTypeKey name="dbServerType" caseSensitive="false" />
		</complexType>
	</metadataIndex>
	<metadataIndex metadata="someTest" index="SomeAttrib3">
		...
	</metadataIndex>


shared
	<specificCase word="db" translation="DB" />
	<specificCase word="dbCollationName" translation="DBCollationName" />

	<complexType name="dbConnectionType">
		<complexTypeKey name="configMode" caseSensitive="false" />
	</complexType>

	<complexType name="dbType">
		<complexTypeKey name="dbServerType" caseSensitive="false" />
	</complexType>
-->

		<metadataIndex 
			metadata="metadataExtended" 
			index="ApplicationName" />
		<metadataIndex 
			metadata="metadataDB" 
			index="ApplicationName" />
		<metadataIndex 
			metadata="metadataBusiness" 
			index="ApplicationName" />
<!--
		<metadataIndex 
			metadata="metadata" 
			index="ApplicationName" />
		<metadataIndex 
			metadata="someTest" 
			index="SomeAttrib3" />
-->

		<specificCase word="db" translation="DB" />
		<specificCase word="dbCollationName" translation="DBCollationName" />
		<specificCase word="dbConnection" translation="DBConnection" />
		<specificCase word="dbConnections" translation="DBConnections" />
		<specificCase word="dbConnectionType" translation="DBConnectionType" />
		<specificCase word="dbConnectionsType" translation="DbConnectionsType" />
		<specificCase word="dbDefaultValue" translation="DBDefaultValue" />
		<specificCase word="dbDescription" translation="DBDescription" />
		<specificCase word="dbFieldName" translation="DBFieldName" />
		<specificCase word="dbs" translation="DBs" />
		<specificCase word="dbServerType" translation="DBServerType" />
		<specificCase word="dbTableName" translation="DBTableName" />
		<specificCase word="dbType" translation="DBType" />
		<specificCase word="fkFieldName" translation="FKFieldName" />
		<specificCase word="fkTableName" translation="FKTableName" />
		<specificCase word="sqlScriptOption" translation="SQLScriptOption" />
		<specificCase word="sqlScriptOptionEnumeration" translation="SQLScriptOptionEnumeration" />

		<specificCase word="applicationName" translation="ApplicationName" />
		<specificCase word="applicationNamespace" translation="ApplicationNamespace" />
		<specificCase word="subAppName" translation="SubAppName" />
		<specificCase word="pseudoReflectionable" translation="PseudoReflectionable" />
		<specificCase word="guidDatalayer" translation="GUIDDatalayer" />
		<specificCase word="guidDatalayer_proxy" translation="GUIDDatalayer_proxy" />
		<specificCase word="guidDatalayer_UTs" translation="GUIDDatalayer_UTs" />
		<specificCase word="guidBusinesslayer" translation="GUIDBusinesslayer" />
		<specificCase word="guidBusinesslayer_proxy" translation="GUIDBusinesslayer_proxy" />
		<specificCase word="guidBusinesslayer_UTs" translation="GUIDBusinesslayer_UTs" />
		<specificCase word="guidDistributedlayer_webservices_server" translation="GUIDDistributedlayer_webservices_server" />
		<specificCase word="guidDistributedlayer_webservices_client" translation="GUIDDistributedlayer_webservices_client" />
		<specificCase word="guidDistributedlayer_remoting_server" translation="GUIDDistributedlayer_remoting_server" />
		<specificCase word="guidDistributedlayer_remoting_client" translation="GUIDDistributedlayer_remoting_client" />
		<specificCase word="guidTest" translation="GUIDTest" />
		<specificCase word="feedbackEmailAddress" translation="FeedbackEmailAddress" />
		<specificCase word="copyrightText" translation="CopyrightText" />
		<specificCase word="copyrightTextLong" translation="CopyrightTextLong" />

		<specificCase word="generateSQL" translation="generateSQL" />
		<specificCase word="isConfig" translation="isConfig" />
		<specificCase word="isConfig_Config" translation="isConfig_Config" />
		<specificCase word="isConfig_Datatype" translation="isConfig_Datatype" />
		<specificCase word="isConfig_Name" translation="isConfig_Name" />
		<specificCase word="isDefault" translation="isDefault" />
		<specificCase word="isExplicitUniqueIndex" translation="isExplicitUniqueIndex" />
		<specificCase word="isIdentity" translation="isIdentity" />
		<specificCase word="isIndexed_andReadOnly" translation="isIndexed_andReadOnly" />
		<specificCase word="isListItemText" translation="isListItemText" />
		<specificCase word="isListItemValue" translation="isListItemValue" />
		<specificCase word="isNullable" translation="isNullable" />
		<specificCase word="isPK" translation="isPK" />
		<specificCase word="isViewPK" translation="isViewPK" />
		<specificCase word="isRange" translation="isRange" />
		<specificCase word="isVirtualTable" translation="isVirtualTable" />

		<specificCase word="isParams" translation="isParams" />
		<specificCase word="isOut" translation="isOut" />
		<specificCase word="isRef" translation="isRef" />

		<!-- caseSensitive="true" -->
		<complexType name="dbConnectionType">
			<complexTypeKey name="configMode" caseSensitive="true" />
		</complexType>
		<complexType name="dbType">
			<complexTypeKey name="dbServerType" caseSensitive="true" />
		</complexType>
		<complexType name="tableDBType">
			<complexTypeKey name="dbServerType" caseSensitive="true" />
		</complexType>
		<complexType name="tableFieldDBType">
			<complexTypeKey name="dbServerType" caseSensitive="true" />
		</complexType>
		<complexType name="tableSearchType">
			<complexTypeKey name="name" caseSensitive="true" />
		</complexType>
		<complexType name="tableSearchUpdateType">
			<complexTypeKey name="name" caseSensitive="true" />
		</complexType>
		<complexType name="tableUpdateType">
			<complexTypeKey name="name" caseSensitive="true" />
		</complexType>

		<!-- caseSensitive="false" -->
		<complexType name="tableFieldRefType">
			<complexTypeKey name="paramName" caseSensitive="false" />
		</complexType>
		<complexType name="tableFieldType">
			<complexTypeKey name="name" caseSensitive="false" />
		</complexType>
		<complexType name="tableType">
			<complexTypeKey name="name" caseSensitive="false" />
		</complexType>

		<complexType name="classType">
			<complexTypeKey name="name" caseSensitive="false" />
		</complexType>
		<complexType name="methodType">
			<complexTypeKey name="name" caseSensitive="false" />
		</complexType>
		<complexType name="parameterType">
			<complexTypeKey name="name" caseSensitive="false" />
		</complexType>

<!--
		<complexType name="tableDBsType">
			<complexTypeKey name="" caseSensitive="true" />
		</complexType>
		<complexType name="tableFieldsType">
			<complexTypeKey name="" caseSensitive="true" />
		</complexType>
		<complexType name="tableSearchesType">
			<complexTypeKey name="" caseSensitive="true" />
		</complexType>
		<complexType name="tableSearchParametersType">
			<complexTypeKey name="" caseSensitive="true" />
		</complexType>
		<complexType name="tableSearchUpdateParametersType">
			<complexTypeKey name="" caseSensitive="true" />
		</complexType>
		<complexType name="tableSearchUpdatesType">
			<complexTypeKey name="" caseSensitive="true" />
		</complexType>
		<complexType name="tableUpdatesType">
			<complexTypeKey name="" caseSensitive="true" />
		</complexType>
-->
</metadata>
